{"openapi":"3.0.0","servers":[{"url":"http://example.com","description":"","variables":{}}],"info":{"version":"a6e5b91c-5fa2-4794-8a6d-707ee436769e","title":"Djib-Non-RPC","description":"","termsOfService":"","contact":{},"license":{"name":""}},"paths":{"/upload":{"post":{"summary":"Upload","operationId":"Upload","parameters":[],"responses":{"200":{"description":"","headers":{}}},"requestBody":{"required":true,"content":{"multipart/form-data":{"schema":{"type":"object","required":["file","txid","publickey","type"],"properties":{"file":{"type":"string","format":"binary"},"txid":{"type":"string","example":"GShCTGLACnApiEQ16WJomKr2qC28Dz3V2jKXWdoJT3yfUVnSCHR3DhLJhV7z4NPsL8tY1gcS7H63YN95cmvMSbg"},"publickey":{"type":"string","example":"9vwHTmut1oxDk1GoZwzFiCD1JRBycRYMewnki5Pt6Ft2"},"type":{"type":"string","example":"public"}}},"example":[{"key":"files[]","type":"file","src":"/C:/Users/Moham/Pictures/photo_2020-12-26_16-46-30.jpg"},{"key":"txid","value":"GShCTGLACnApiEQ16WJomKr2qC28Dz3V2jKXWdoJT3yfUVnSCHR3DhLJhV7z4NPsL8tY1gcS7H63YN95cmvMSbg","type":"text"},{"key":"publickey","value":"9vwHTmut1oxDk1GoZwzFiCD1JRBycRYMewnki5Pt6Ft2","type":"text"},{"key":"type","value":"public","type":"text"},{"key":"signature","value":"3KpK4TBVLMY4fSsha8preQFpsEAkDAebgx85u9HD2B9tdCeYjbtnBaUfhBcWLZsVtpN4aQZjWss2tQxXYnYAQz4E","type":"text","disabled":true},{"key":"pth","value":"myfilew/","type":"text","disabled":true}]}}}}},"/health":{"post":{"summary":"health check","operationId":"healthcheck","parameters":[],"responses":{"200":{"description":"","headers":{}}}}}},"components":{},"security":[],"tags":[],"externalDocs":{"url":"","description":""},"warnings":[]}